kodiak/__init__.py
kodiak/args_dict_builder.py
kodiak/args_parser.py
kodiak/colbuilders.py
kodiak/config.py
kodiak/kodiak_dataframe.py
kodiak/transforms.py
kodiak-0.1.0.dist-info/DESCRIPTION.rst
kodiak-0.1.0.dist-info/METADATA
kodiak-0.1.0.dist-info/RECORD
kodiak-0.1.0.dist-info/WHEEL
kodiak-0.1.0.dist-info/metadata.json
kodiak-0.1.0.dist-info/top_level.txt
