Metadata-Version: 2.0
Name: kodiak
Version: 0.1.0
Summary: A library to enhance your feature engineering workflow
Home-page: https://github.com/alejandrodumas/kodiak
Author: Ezequiel Erbaro
Author-email: eerbaro@gmail.com
License: MIT license
Keywords: kodiak,pandas
Platform: UNKNOWN
Classifier: Development Status :: 2 - Pre-Alpha
Classifier: Intended Audience :: Developers
Classifier: License :: OSI Approved :: MIT License
Classifier: Natural Language :: English
Classifier: Programming Language :: Python :: 2
Classifier: Programming Language :: Python :: 2.6
Classifier: Programming Language :: Python :: 2.7
Classifier: Programming Language :: Python :: 3
Classifier: Programming Language :: Python :: 3.3
Classifier: Programming Language :: Python :: 3.4
Classifier: Programming Language :: Python :: 3.5
Requires-Dist: pandas
